log_proxy/__init__.py
log_proxy/__main__.py
log_proxy/base.py
log_proxy/forwarders.py
log_proxy/handlers.py
log_proxy/server.py
log_proxy/utils.py
log_proxy/watcher.py
log_proxy-2.0.dist-info/LICENSE
log_proxy-2.0.dist-info/METADATA
log_proxy-2.0.dist-info/WHEEL
log_proxy-2.0.dist-info/entry_points.txt
log_proxy-2.0.dist-info/top_level.txt
log_proxy-2.0.dist-info/RECORD
