Metadata-Version: 2.1
Name: log-proxy
Version: 2.0
Summary: Proxy the log from one system to another
Home-page: https://github.com/fkantelberg/log-proxy
Author: Florian Kantelberg
Author-email: florian.kantelberg@mailbox.org
License: MIT
Keywords: logging socket proxy
Platform: UNKNOWN
Classifier: Programming Language :: Python :: 3
Classifier: License :: OSI Approved :: MIT License
Classifier: Operating System :: OS Independent
Requires-Python: >=3.7
License-File: LICENSE
Provides-Extra: mongodb
Requires-Dist: pymongo ; extra == 'mongodb'
Provides-Extra: observe
Requires-Dist: watchdog ; extra == 'observe'
Provides-Extra: postgres
Requires-Dist: asyncpg ; extra == 'postgres'
